bshm/__init__.py
bshm/bashmator.py
bshm/bones/__init__.py
bshm/bones/config.py
bshm/bones/funcs.py
bshm/bones/library.py
bshm/bones/msg.py
bshm/bones/validate.py
bshm/bones/yamlscript.py
bshm/library/files/lorem/lorem.txt
bshm/library/modules/examples/args/choice.yaml
bshm/library/modules/examples/args/choice_default.yaml
bshm/library/modules/examples/args/default.yaml
bshm/library/modules/examples/args/default_empty.yaml
bshm/library/modules/examples/args/flag.yaml
bshm/library/modules/examples/args/metavar.yaml
bshm/library/modules/examples/args/multiple.yaml
bshm/library/modules/examples/args/regex.yaml
bshm/library/modules/examples/args/replacer.yaml
bshm/library/modules/examples/args/simple.yaml
bshm/library/modules/examples/files/replacer.yaml
bshm/library/modules/examples/files/simple.yaml
bshm/library/modules/examples/items/default.yaml
bshm/library/modules/examples/items/mode.yaml
bshm/library/modules/examples/items/shell.yaml
bshm/library/modules/examples/items/simple.yaml
bshm/library/modules/examples/minimal.yaml
bshm/library/modules/examples/mode/format.yaml
bshm/library/modules/examples/mode/format_empty.yaml
bshm/library/modules/examples/mode/join.yaml
bshm/library/modules/examples/mode/loop.yaml
bshm/library/modules/examples/mode/pformat.yaml
bshm/library/modules/examples/mode/readfile.yaml
bshm/library/modules/examples/mode/replace.yaml
bshm/library/modules/examples/simple.yaml
bashmator-1.1.8.dist-info/LICENSE
bashmator-1.1.8.dist-info/METADATA
bashmator-1.1.8.dist-info/WHEEL
bashmator-1.1.8.dist-info/entry_points.txt
bashmator-1.1.8.dist-info/RECORD
