Metadata-Version: 2.1
Name: bashmator
Version: 1.1.8
Summary: Console script manager based on YAML format
Home-page: https://github.com/vinzekatze/bashmator
License: MIT
Author: vinzekatze
Author-email: vinzekatze@gmail.com
Requires-Python: >=3.10,<4.0
Classifier: License :: OSI Approved :: MIT License
Classifier: Programming Language :: Python :: 3
Classifier: Programming Language :: Python :: 3.10
Classifier: Programming Language :: Python :: 3.11
Classifier: Programming Language :: Python :: 3.12
Requires-Dist: appdirs (>=1.4.4,<2.0.0)
Requires-Dist: colorama (>=0.4.6,<0.5.0)
Requires-Dist: pyyaml (>=6.0.1,<7.0.0)
Requires-Dist: tabulate (>=0.9.0,<0.10.0)
Project-URL: Repository, https://github.com/vinzekatze/bashmator
